{
  "indexes": [
    {
      "collectionGroup": "scripts",
      "queryScope": "COLLECTION",
      "fields": [
        { "fieldPath": "titleLowerCase", "order": "ASCENDING" },
        { "fieldPath": "createdAt", "order": "DESCENDING" }
      ]
    },
    {
      "collectionGroup": "scripts",
      "queryScope": "COLLECTION",
      "fields": [
        { "fieldPath": "language", "order": "ASCENDING" },
        { "fieldPath": "createdAt", "order": "DESCENDING" }
      ]
    },
    {
      "collectionGroup": "scripts",
      "queryScope": "COLLECTION",
      "fields": [
        { "fieldPath": "tags", "arrayConfig": "CONTAINS" },
        { "fieldPath": "createdAt", "order": "DESCENDING" }
      ]
    },
    {
      "collectionGroup": "scripts",
      "queryScope": "COLLECTION",
      "fields": [
        { "fieldPath": "titleLowerCase", "order": "ASCENDING" },
        { "fieldPath": "likes", "order": "DESCENDING" }
      ]
    },
    {
      "collectionGroup": "scripts",
      "queryScope": "COLLECTION",
      "fields": [
        { "fieldPath": "language", "order": "ASCENDING" },
        { "fieldPath": "likes", "order": "DESCENDING" }
      ]
    },
    {
      "collectionGroup": "scripts",
      "queryScope": "COLLECTION",
      "fields": [
        { "fieldPath": "tags", "arrayConfig": "CONTAINS" },
        { "fieldPath": "likes", "order": "DESCENDING" }
      ]
    }
  ],
  "fieldOverrides": []
}
